marketo_monkey/__init__.py
marketo_monkey/__main__.py
marketo_monkey-0.3.data/scripts/marketo-monkey.py
marketo_monkey-0.3.dist-info/METADATA
marketo_monkey-0.3.dist-info/RECORD
marketo_monkey-0.3.dist-info/WHEEL
marketo_monkey-0.3.dist-info/top_level.txt
