Metadata-Version: 2.1
Name: marketo-monkey
Version: 0.3
Summary: CLI tool to facilitate Marketo integration
Home-page: https://github.com/cprov/marketo-monkey
Author: Celso Providelo
Author-email: celso.providelo@canonical.com
License: LICENSE
Platform: UNKNOWN
Classifier: Programming Language :: Python :: 3
Classifier: License :: OSI Approved :: MIT License
Classifier: Operating System :: OS Independent
Requires-Dist: python-editor
Requires-Dist: PyYAML
Requires-Dist: requests
